odoo/addons/delivery_package_number_default/README.rst
odoo/addons/delivery_package_number_default/__init__.py
odoo/addons/delivery_package_number_default/__manifest__.py
odoo/addons/delivery_package_number_default/models/__init__.py
odoo/addons/delivery_package_number_default/models/stock_picking.py
odoo/addons/delivery_package_number_default/models/stock_picking_type.py
odoo/addons/delivery_package_number_default/readme/CONFIGURE.md
odoo/addons/delivery_package_number_default/readme/CONTRIBUTORS.md
odoo/addons/delivery_package_number_default/readme/DESCRIPTION.md
odoo/addons/delivery_package_number_default/readme/USAGE.md
odoo/addons/delivery_package_number_default/static/description/icon.png
odoo/addons/delivery_package_number_default/static/description/index.html
odoo/addons/delivery_package_number_default/tests/__init__.py
odoo/addons/delivery_package_number_default/tests/test_delivery_package_number_default.py
odoo/addons/delivery_package_number_default/views/stock_picking_type_views.xml
odoo_addon_delivery_package_number_default-17.0.1.0.0.1.dist-info/METADATA
odoo_addon_delivery_package_number_default-17.0.1.0.0.1.dist-info/WHEEL
odoo_addon_delivery_package_number_default-17.0.1.0.0.1.dist-info/top_level.txt
odoo_addon_delivery_package_number_default-17.0.1.0.0.1.dist-info/RECORD
